agent_mcp/__init__.py
agent_mcp/config.py
agent_mcp/server.py
agent_mcp/tools/__init__.py
agent_mcp/tools/navigation.py
agent_mcp/tools/read.py
agent_mcp/tools/search.py
agent_mcp/utils/__init__.py
agent_mcp/utils/file_detector.py
agent_mcp/utils/logger.py
agent_mcp/validators/__init__.py
agent_mcp/validators/path_validator.py
context_mcp-0.1.0.dist-info/METADATA
context_mcp-0.1.0.dist-info/WHEEL
context_mcp-0.1.0.dist-info/entry_points.txt
context_mcp-0.1.0.dist-info/licenses/LICENSE
context_mcp-0.1.0.dist-info/RECORD
