Metadata-Version: 2.4
Name: context-mcp
Version: 0.1.0
Summary: MCP server for project context integration - provides read-only filesystem operations for AI agents
Project-URL: Homepage, https://github.com/geq1fan/context-mcp
Project-URL: Documentation, https://github.com/geq1fan/context-mcp#readme
Project-URL: Repository, https://github.com/geq1fan/context-mcp
Project-URL: Bug Tracker, https://github.com/geq1fan/context-mcp/issues
Project-URL: Changelog, https://github.com/geq1fan/context-mcp/blob/main/CHANGELOG.md
Author-email: Context MCP Team <context-mcp@example.com>
Maintainer-email: Context MCP Team <context-mcp@example.com>
License: MIT
License-File: LICENSE
Keywords: agent,ai,claude,code-analysis,context-integration,fastmcp,mcp,model-context-protocol
Classifier: Development Status :: 4 - Beta
Classifier: Intended Audience :: Developers
Classifier: License :: OSI Approved :: MIT License
Classifier: Programming Language :: Python :: 3
Classifier: Programming Language :: Python :: 3.11
Classifier: Programming Language :: Python :: 3.12
Classifier: Programming Language :: Python :: 3.13
Classifier: Topic :: Scientific/Engineering :: Artificial Intelligence
Classifier: Topic :: Software Development :: Code Generators
Classifier: Topic :: Software Development :: Libraries :: Python Modules
Requires-Python: >=3.11
Requires-Dist: chardet>=5.0.0
Requires-Dist: fastmcp>=0.1.0
